mdlu/__init__.py
mdlu/memory_estimator.py
mdlu/transforms.py
mdlu/utils.py
mdlu/data/__init__.py
mdlu/data/dataset.py
mdlu/data/modality.py
mdlu/metrics/__init__.py
mdlu/metrics/moving_avg.py
mdlu/metrics/single_class.py
tests/data/test_modality.py
medical_dl_utils-0.1.6.dist-info/LICENSE
medical_dl_utils-0.1.6.dist-info/METADATA
medical_dl_utils-0.1.6.dist-info/WHEEL
medical_dl_utils-0.1.6.dist-info/top_level.txt
medical_dl_utils-0.1.6.dist-info/zip-safe
medical_dl_utils-0.1.6.dist-info/RECORD
