Metadata-Version: 2.1
Name: medical-dl-utils
Version: 0.1.6
Summary: Helpful utilities for deep learning in medical image analysis/medical image computing
Author: Justus Schock
Author-email: justus.schock@posteo.de
Maintainer-email: Justus Schock <justus.schock@posteo.de>
License: Apache License
Project-URL: Homepage, https://github.com/justusschock/medical-dl-utils
Project-URL: Repository, https://github.com/justusschock/medical-dl-utils
Project-URL: Bug Reports, https://github.com/justusschock/medical-dl-utils/issues
Keywords: deep learning,machine learning,pytorch,medical,healthcare,AI
Classifier: Programming Language :: Python :: 3
Requires-Python: >=3.7
License-File: LICENSE
Requires-Dist: torch (<=1.11,>=1.9)
Requires-Dist: psutil (<=5.9.1)
Requires-Dist: torchio (<=0.18.78,>0.18.56)
Requires-Dist: pytorch-lightning (<=1.6.4,>=1.5)
Requires-Dist: monai (<=0.8.1,>=0.7)
Provides-Extra: test
Requires-Dist: pytest ; extra == 'test'
Requires-Dist: coverage ; extra == 'test'
